MANIFEST.in
README.md
setup.cfg
setup.py
docassemble_textstat/__init__.py
docassemble_textstat/textstat.py
docassemble_textstat.egg-info/PKG-INFO
docassemble_textstat.egg-info/SOURCES.txt
docassemble_textstat.egg-info/dependency_links.txt
docassemble_textstat.egg-info/not-zip-safe
docassemble_textstat.egg-info/requires.txt
docassemble_textstat.egg-info/top_level.txt
docassemble_textstat/resources/en/easy_words.txt
docassemble_textstat/resources/es/easy_words.txt