Metadata-Version: 2.1
Name: docassemble-textstat
Version: 0.7.0
Summary: Calculate statistical features from text
Home-page: https://github.com/shivam5992/textstat
Author: Shivam Bansal, Chaitanya Aggarwal
Author-email: shivam5992@gmail.com
License: MIT
Platform: UNKNOWN
Classifier: Programming Language :: Python
Classifier: Programming Language :: Python :: 3
Classifier: Programming Language :: Python :: 3.6
Classifier: Programming Language :: Python :: 3.7
Classifier: Programming Language :: Python :: 3.8
Classifier: Programming Language :: Python :: 3 :: Only
Classifier: Intended Audience :: Developers
Classifier: Intended Audience :: Education
Classifier: Intended Audience :: Science/Research
Classifier: Topic :: Text Processing
Requires-Python: >=3.6
